chad/__init__.py
chad/__main__.py
chad/installer.py
chad/investigation_report.py
chad/mcp_config.py
chad/mcp_playwright.py
chad/model_catalog.py
chad/prompts.py
chad/provider_ui.py
chad/providers.py
chad/screenshot_fixtures.py
chad/security.py
chad/session_logger.py
chad/ui_playwright_runner.py
chad/utils.py
chad/visual_test_map.py
chad/web_ui.py
chad_ai-0.5.0.dist-info/METADATA
chad_ai-0.5.0.dist-info/WHEEL
chad_ai-0.5.0.dist-info/entry_points.txt
chad_ai-0.5.0.dist-info/top_level.txt
chad_ai-0.5.0.dist-info/RECORD
