Metadata-Version: 2.4
Name: chad-ai
Version: 0.5.0
Summary: Chad: YOLO AI
Author: Team Chad: AI Police
Classifier: Development Status :: 3 - Alpha
Classifier: Intended Audience :: Developers
Classifier: Topic :: Software Development :: Build Tools
Classifier: Programming Language :: Python :: 3
Classifier: Programming Language :: Python :: 3.8
Classifier: Programming Language :: Python :: 3.9
Classifier: Programming Language :: Python :: 3.10
Classifier: Programming Language :: Python :: 3.11
Classifier: Programming Language :: Python :: 3.12
Requires-Python: >=3.8
Requires-Dist: requests>=2.31.0
Requires-Dist: bcrypt>=4.0.0
Requires-Dist: cryptography>=41.0.0
Requires-Dist: gradio>=4.0.0
Requires-Dist: pexpect>=4.9.0
Provides-Extra: dev
Requires-Dist: pytest>=7.4.0; extra == "dev"
Requires-Dist: black>=23.0.0; extra == "dev"
Requires-Dist: flake8>=6.0.0; extra == "dev"
Requires-Dist: mypy>=1.0.0; extra == "dev"
Requires-Dist: playwright>=1.40.0; extra == "dev"
Requires-Dist: mcp>=1.25.0; extra == "dev"
